new_example_package_orl/__init__.py
new_example_package_orl/_version.py
new_example_package_orl/example_module.py
example_project_orl-2.0.0.dist-info/LICENSE
example_project_orl-2.0.0.dist-info/METADATA
example_project_orl-2.0.0.dist-info/WHEEL
example_project_orl-2.0.0.dist-info/top_level.txt
example_project_orl-2.0.0.dist-info/RECORD
